opentimelineio_py/__init__.py
opentimelineio_py/exceptions.py
opentimelineio_py/hooks.py
opentimelineio_py/media_linker.py
opentimelineio_py/opentime.py
opentimelineio_py/test_utils.py
opentimelineio_py/adapters/__init__.py
opentimelineio_py/adapters/adapter.py
opentimelineio_py/adapters/builtin_adapters.plugin_manifest.json
opentimelineio_py/adapters/cmx_3600.py
opentimelineio_py/adapters/fcp_xml.py
opentimelineio_py/adapters/otio_json.py
opentimelineio_py/algorithms/__init__.py
opentimelineio_py/algorithms/filter.py
opentimelineio_py/algorithms/stack_algo.py
opentimelineio_py/algorithms/timeline_algo.py
opentimelineio_py/algorithms/track_algo.py
opentimelineio_py/console/__init__.py
opentimelineio_py/console/autogen_plugin_documentation.py
opentimelineio_py/console/autogen_serialized_datamodel.py
opentimelineio_py/console/console_utils.py
opentimelineio_py/console/otiocat.py
opentimelineio_py/console/otioconvert.py
opentimelineio_py/console/otiopluginfo.py
opentimelineio_py/console/otiostat.py
opentimelineio_py/core/__init__.py
opentimelineio_py/core/composable.py
opentimelineio_py/core/composition.py
opentimelineio_py/core/item.py
opentimelineio_py/core/json_serializer.py
opentimelineio_py/core/media_reference.py
opentimelineio_py/core/serializable_object.py
opentimelineio_py/core/type_registry.py
opentimelineio_py/core/unknown_schema.py
opentimelineio_py/plugins/__init__.py
opentimelineio_py/plugins/manifest.py
opentimelineio_py/plugins/python_plugin.py
opentimelineio_py/schema/__init__.py
opentimelineio_py/schema/clip.py
opentimelineio_py/schema/effect.py
opentimelineio_py/schema/external_reference.py
opentimelineio_py/schema/gap.py
opentimelineio_py/schema/generator_reference.py
opentimelineio_py/schema/marker.py
opentimelineio_py/schema/missing_reference.py
opentimelineio_py/schema/schemadef.py
opentimelineio_py/schema/serializable_collection.py
opentimelineio_py/schema/stack.py
opentimelineio_py/schema/timeline.py
opentimelineio_py/schema/track.py
OpenTimelineIO_Py-0.11.0.dev2.dist-info/LICENSE.txt
OpenTimelineIO_Py-0.11.0.dev2.dist-info/METADATA
OpenTimelineIO_Py-0.11.0.dev2.dist-info/NOTICE.txt
OpenTimelineIO_Py-0.11.0.dev2.dist-info/WHEEL
OpenTimelineIO_Py-0.11.0.dev2.dist-info/entry_points.txt
OpenTimelineIO_Py-0.11.0.dev2.dist-info/top_level.txt
OpenTimelineIO_Py-0.11.0.dev2.dist-info/RECORD
