Metadata-Version: 2.1
Name: OpenTimelineIO-Py
Version: 0.11.0.dev2
Summary: Editorial interchange format and API
Home-page: http://opentimeline.io
Author: Pixar Animation Studios
Author-email: opentimelineio@pixar.com
License: Modified Apache 2.0 License
Project-URL: Source, https://github.com/PixarAnimationStudios/OpenTimelineIO
Project-URL: Documentation, https://opentimelineio.readthedocs.io/
Project-URL: Issues, https://github.com/PixarAnimationStudios/OpenTimelineIO/issues
Keywords: film tv editing editorial edit non-linear edl time
Platform: any
Classifier: Development Status :: 4 - Beta
Classifier: Topic :: Multimedia :: Graphics
Classifier: Topic :: Multimedia :: Video
Classifier: Topic :: Multimedia :: Video :: Display
Classifier: Topic :: Multimedia :: Video :: Non-Linear Editor
Classifier: Topic :: Software Development :: Libraries :: Python Modules
Classifier: License :: Other/Proprietary License
Classifier: Programming Language :: Python :: 2
Classifier: Programming Language :: Python :: 2.7
Classifier: Programming Language :: Python :: 3
Classifier: Programming Language :: Python :: 3.6
Classifier: Programming Language :: Python :: 3.7
Classifier: Operating System :: OS Independent
Classifier: Natural Language :: English
Provides-Extra: dev
Requires-Dist: flake8 (>=3.5) ; extra == 'dev'
Requires-Dist: coverage (>=4.5) ; extra == 'dev'
Requires-Dist: tox (>=3.0) ; extra == 'dev'
Requires-Dist: urllib3 (>=1.24.3) ; extra == 'dev'
